{"assets/images/Spotify_icon.png":["assets/images/Spotify_icon.png"],"assets/images/Steam.png":["assets/images/Steam.png"],"assets/images/bg1.png":["assets/images/bg1.png"],"assets/images/bg2.png":["assets/images/bg2.png"],"assets/images/deneme.jpg":["assets/images/deneme.jpg"],"assets/images/rocket.jpg":["assets/images/rocket.jpg"],"assets/images/rocket.json":["assets/images/rocket.json"],"assets/images/space.jpg":["assets/images/space.jpg"],"assets/images/space2.jpg":["assets/images/space2.jpg"],"packages/cupertino_icons/assets/CupertinoIcons.ttf":["packages/cupertino_icons/assets/CupertinoIcons.ttf"]}