{"assets/images/Spotify_icon.png":["assets/images/Spotify_icon.png"],"assets/images/rocket.jpg":["assets/images/rocket.jpg"],"assets/images/rocket.json":["assets/images/rocket.json"],"assets/images/space.jpg":["assets/images/space.jpg"],"assets/images/space2.jpg":["assets/images/space2.jpg"],"assets/images/spacedata.jpg":["assets/images/spacedata.jpg"],"assets/images/steam.png":["assets/images/steam.png"],"packages/cupertino_icons/assets/CupertinoIcons.ttf":["packages/cupertino_icons/assets/CupertinoIcons.ttf"]}